{
  "required": true,
  "minVersion": "0.8",
  "package": "github.thesivlerecho.zeropoint.mixin",
  "compatibilityLevel": "JAVA_8",
  "mixins": [
    "AbstractButtonWidgetMixin",
    "AbstractClientPlayerEntityMixin",
    "BipedEntityModelMixin",
    "BossBarHudMixin",
    "BufferBuilderStorageMixin",
    "CameraMixin",
    "GameRendererMixin",
    "HandledScreenMixin",
    "InGameHudMixin",
    "ItemRendererMixin",
    "MerchantScreenMixin",
    "MouseMixin",
    "PlayerEntityRendererMixin",
    "PlayerListEntryMixin",
    "SplashScreenMixin",
    "SpriteAtlasTextureMixin",
    "TextRendererMixin",
    "TitleScreenMixin",
    "ScreenMixin",
    "WorldRendererMixin"
  ],
  "client": [
  ],
  "injectors": {
    "defaultRequire": 1
  }
}
